<?xml version="1.0" encoding="UTF-8"?>
<XXQGEN_RCV_RCT_NUM_DTL_AK>
<P_RECEIPT_NUM>5006</P_RECEIPT_NUM>
<LIST_G_MAIN>
<G_MAIN>
<STORAGE_LOCATION>C1.1.1..</STORAGE_LOCATION>
<RECEIPT_NUM>5006</RECEIPT_NUM>
<COUNTRY>US</COUNTRY>
<COUNTRY>US</COUNTRY>
<INCOTERMS>Origin</INCOTERMS>
<INCOTERMS>Origin</INCOTERMS>
<CURRENCY_CODE>USD</CURRENCY_CODE>
<ACCOUNT_NUMBER>10271-17621-987</ACCOUNT_NUMBER>
<LIST_G2_MAIN>
<G2_MAIN>
<ITEM>WM107</ITEM>
<DESCRIPTION>Multi Function Printer</DESCRIPTION>
<QTY>25</QTY>
<UOM>Ea</UOM>
<COMODITY_CODE/>
<COUNTRY>US</COUNTRY>
<UNIT_WEIGHT>12</UNIT_WEIGHT>
<UNIT_WEIGHT>12</UNIT_WEIGHT>
<NET_VALUE>6293.75</NET_VALUE>
<QUANTITY>25</QUANTITY>
<QUANTITY>25</QUANTITY>
<PO_NUMBER>3005</PO_NUMBER>
<GL_DATE>2001-08-06T10:40:55.000-04:00</GL_DATE>
</G2_MAIN>
</LIST_G2_MAIN>
</G_MAIN>
</LIST_G_MAIN>
</XXQGEN_RCV_RCT_NUM_DTL_AK>